ralf/__init__.py
ralf/ralf.py
test/__init__.py
test/test_ralf.py
ralf-0.0.1.dist-info/LICENSE
ralf-0.0.1.dist-info/METADATA
ralf-0.0.1.dist-info/WHEEL
ralf-0.0.1.dist-info/top_level.txt
ralf-0.0.1.dist-info/RECORD
