Metadata-Version: 2.1
Name: ralf
Version: 0.0.1
Summary: Rotation Angle Limit Finder
Home-page: https://github.com/JacksonBurns/ralf
Author: Jackson Burns
License: MIT
Classifier: Programming Language :: Python :: 3
License-File: LICENSE
Requires-Dist: scoria
